redmine_mcp/__init__.py
redmine_mcp/config.py
redmine_mcp/redmine_client.py
redmine_mcp/server.py
redmine_mcp/validators.py
redmine_mcp-0.0.1.dist-info/METADATA
redmine_mcp-0.0.1.dist-info/WHEEL
redmine_mcp-0.0.1.dist-info/entry_points.txt
redmine_mcp-0.0.1.dist-info/licenses/LICENSE
redmine_mcp-0.0.1.dist-info/RECORD
