Metadata-Version: 2.4
Name: redmine-mcp
Version: 0.0.1
Summary: Redmine MCP server for Claude Code - manage Redmine issues via MCP tools
Project-URL: Homepage, https://github.com/your-username/redmine-mcp
Project-URL: Bug Reports, https://github.com/your-username/redmine-mcp/issues
Project-URL: Source, https://github.com/your-username/redmine-mcp
Project-URL: Documentation, https://github.com/your-username/redmine-mcp/blob/main/README.md
Author-email: Jack Tsai <snowild@gmail.com>, Bruno Izaguirre <bruno.izagumart@gmail.com>
Maintainer-email: Jack Tsai <snowild@gmail.com>
License: MIT
License-File: LICENSE
Keywords: api,claude,mcp,project-management,redmine
Classifier: Development Status :: 4 - Beta
Classifier: Intended Audience :: Developers
Classifier: License :: OSI Approved :: MIT License
Classifier: Operating System :: OS Independent
Classifier: Programming Language :: Python :: 3
Classifier: Programming Language :: Python :: 3.12
Classifier: Programming Language :: Python :: 3.13
Classifier: Topic :: Office/Business :: Groupware
Classifier: Topic :: Software Development :: Libraries :: Python Modules
Classifier: Topic :: System :: Systems Administration
Requires-Python: >=3.12
Requires-Dist: mcp[cli]>=1.9.4
Requires-Dist: python-dotenv>=1.0.0
Requires-Dist: requests>=2.31.0
Provides-Extra: dev
Requires-Dist: pytest-cov>=6.2.1; extra == 'dev'
Requires-Dist: pytest>=8.4.1; extra == 'dev'
